CHANGELOG.rst
LICENSE.txt
MANIFEST.in
README.rst
setup.py
tox.ini
slapos/__init__.py
slapos.recipe.cmmi.egg-info/PKG-INFO
slapos.recipe.cmmi.egg-info/SOURCES.txt
slapos.recipe.cmmi.egg-info/dependency_links.txt
slapos.recipe.cmmi.egg-info/entry_points.txt
slapos.recipe.cmmi.egg-info/namespace_packages.txt
slapos.recipe.cmmi.egg-info/not-zip-safe
slapos.recipe.cmmi.egg-info/requires.txt
slapos.recipe.cmmi.egg-info/top_level.txt
slapos/recipe/__init__.py
slapos/recipe/cmmi/README-SlapOS.rst
slapos/recipe/cmmi/README.rst
slapos/recipe/cmmi/__init__.py
slapos/recipe/cmmi/tests.py
slapos/recipe/cmmi/testdata/Foo-Bar-0.0.0.tar.gz
slapos/recipe/cmmi/testdata/haproxy-1.4.8-dummy.tar.gz
slapos/recipe/cmmi/testdata/package-0.0.0.tar.gz