Metadata-Version: 2.1
Name: slapos.recipe.cmmi
Version: 0.22
Summary: zc.buildout recipe for compiling and installing source distributions.
Home-page: https://lab.nexedi.com/nexedi/slapos.recipe.cmmi
Author: Nexedi
Author-email: info@nexedi.com
License: BSD
Keywords: development buildout recipe
Classifier: Framework :: Buildout :: Recipe
Classifier: Framework :: Buildout
Classifier: Intended Audience :: Developers
Classifier: License :: OSI Approved :: BSD License
Classifier: Topic :: Software Development :: Build Tools
Classifier: Topic :: Software Development :: Libraries :: Python Modules
Provides-Extra: test
License-File: LICENSE.txt
